CHANGES.rst
COPYING.LGPLv3
MANIFEST.in
README.rst
setup.py
django_inplaceedit_bootstrap.egg-info/PKG-INFO
django_inplaceedit_bootstrap.egg-info/SOURCES.txt
django_inplaceedit_bootstrap.egg-info/dependency_links.txt
django_inplaceedit_bootstrap.egg-info/not-zip-safe
django_inplaceedit_bootstrap.egg-info/requires.txt
django_inplaceedit_bootstrap.egg-info/top_level.txt
inplaceeditform_bootstrap/__init__.py
inplaceeditform_bootstrap/fields.py
inplaceeditform_bootstrap/settings.py
inplaceeditform_bootstrap/static/adaptor_tiny/css/adaptor_tiny.css
inplaceeditform_bootstrap/static/css/inplaceedit_structure.css
inplaceeditform_bootstrap/static/css/inplaceedit_structure.less
inplaceeditform_bootstrap/static/js/jquery.inplaceeditform.hooks.js
inplaceeditform_bootstrap/templates/inplaceeditform/inc.extra_options.html
inplaceeditform_bootstrap/templates/inplaceeditform/inc.inplace_toolbar.html
inplaceeditform_bootstrap/templates/inplaceeditform/render_field.html
inplaceeditform_bootstrap/templates/inplaceeditform/adaptor_file/render_field.html
inplaceeditform_bootstrap/templates/inplaceeditform_bootstrap/extra_options.html
inplaceeditform_bootstrap/templates/inplaceeditform_bootstrap/adaptor_date/render_value_edit.html
inplaceeditform_bootstrap/templatetags/__init__.py
inplaceeditform_bootstrap/templatetags/inplace_edit_bootstrap.py