Metadata-Version: 1.1
Name: django-inplaceedit-bootstrap
Version: 0.2.1
Summary: Integration of django-inplaceedit and bootstrap
Home-page: https://github.com/django-inplaceedit/django-inplaceedit-bootstrap
Author: Pablo Martin
Author-email: goinnn@gmail.com
License: LGPL 3
Keywords: django,inplace,inline edit,bootstrap,inline form,inline,inplace edit,inplace form,ajax
Platform: UNKNOWN
Classifier: Development Status :: 4 - Beta
Classifier: Framework :: Django
Classifier: License :: OSI Approved :: GNU Library or Lesser General Public License (LGPL)
Classifier: Programming Language :: Python :: 2
Classifier: Programming Language :: Python :: 3
